<?xml version="1.0" encoding="utf-8" ?>
<Defs>

	<ThingCategoryDef>
		<defName>BasicProstheses</defName>
		<label>basic prostheses</label>
		<parent>BodyPartsArtificial</parent>
	</ThingCategoryDef>

	<ThingCategoryDef>
		<defName>SimpleProstheses</defName>
		<label>simple prostheses</label>
		<parent>BodyPartsArtificial</parent>
	</ThingCategoryDef>

	<ThingCategoryDef>
		<defName>BionicProstheses</defName>
		<label>bionic prostheses</label>
		<parent>BodyPartsArtificial</parent>
	</ThingCategoryDef>

	<ThingCategoryDef>
		<defName>ArchotechProstheses</defName>
		<label>archotech prostheses</label>
		<parent>BodyPartsArtificial</parent>
	</ThingCategoryDef>

	<ThingCategoryDef>
		<defName>MSE_ProstheticModules</defName>
		<label>prosthetic modules</label>
		<parent>BodyPartsArtificial</parent>
	</ThingCategoryDef>

	<ThingCategoryDef>
		<defName>Implants</defName>
		<label>implants</label>
		<parent>Items</parent>
	</ThingCategoryDef>

</Defs>