<?xml version="1.0" encoding="utf-8" ?>
<Defs>


	<!-- cnn forearm -->

	<HediffDef ParentName="CNHediffProsthetic">
		<defName>CNNetworkedForearm</defName>
		<label>networked arm</label>
		<labelNoun>a networked forearm</labelNoun>
		<description>A networked prosthetic that offloads processing to remote processors. Cheaper than self contained bionic forearms, and more efficient, but requires infrastructure to function.</description>
		<spawnThingOnRemoved>CNNetworkedForearm</spawnThingOnRemoved>
		<comps>
			<li Class="CyberNet.HediffCompPropertiesCyberNetImplant">
				<compClass>CyberNet.HediffCompCyberNetImplant</compClass>
				<DefaultSeverity>1</DefaultSeverity>
				<BandwidthUsage>0.1</BandwidthUsage>
				<ProcessorUsage>0.05</ProcessorUsage>
			</li>
		</comps>
	</HediffDef>

	<ThingDef ParentName="CyberNetProsthetic">
		<defName>CNNetworkedForearm</defName>
		<label>Networked forearm</label>
		<description>A networked prosthetic that offloads processing to remote processors. Cheaper than self contained bionic arms, and more efficient, but requires infrastructure to function.</description>
		<statBases>
			<WorkToMake>25000</WorkToMake>
			<Mass>3.5</Mass>
		</statBases>
		<costList>
			<Plasteel>8</Plasteel>
			<ComponentIndustrial>4</ComponentIndustrial>
			<ComponentSpacer>1</ComponentSpacer>
		</costList>
		<recipeMaker>
			<skillRequirements>
				<Crafting>10</Crafting>
			</skillRequirements>
			<researchPrerequisite>CNNetworkedProsthetics</researchPrerequisite>
		</recipeMaker>
		<comps>
			<li Class="MSE2.CompProperties_IncludedChildParts">
				<standardChildren>
					<li>CNNetworkedHand</li>
					<li>BionicInternalSupport</li>
					<li>BionicInternalSupport</li>
				</standardChildren>
			</li>
		</comps>
	</ThingDef>

	<RecipeDef ParentName="CyberNetSurgery">
		<defName>CNInstallNetworkedForearm</defName>
		<label>Install networked forearm</label>
		<description>Install a networked forearm</description>
		<jobString>Installing networked forearm</jobString>
		<workAmount>2500</workAmount>
		<ingredients>
			<li>
				<filter>
					<categories>
						<li>Medicine</li>
					</categories>
				</filter>
				<count>2</count>
			</li>
			<li>
				<filter>
					<thingDefs>
						<li>CNNetworkedForearm</li>
					</thingDefs>
				</filter>
				<count>1</count>
			</li>
		</ingredients>
		<fixedIngredientFilter>
			<categories>
				<li>Medicine</li>
			</categories>
			<thingDefs>
				<li>CNNetworkedForearm</li>
			</thingDefs>
		</fixedIngredientFilter>
		<appliedOnFixedBodyParts>
			<li>Arm</li>
		</appliedOnFixedBodyParts>
		<addsHediff>CNNetworkedForearm</addsHediff>
	</RecipeDef>

	<!-- cnn hand -->

	<HediffDef ParentName="CNHediffProsthetic">
		<defName>CNNetworkedHand</defName>
		<label>networked hand</label>
		<labelNoun>a networked hand</labelNoun>
		<description>A networked prosthetic that offloads processing to remote processors. Cheaper than self contained bionic hands, and more efficient, but requires infrastructure to function.</description>
		<spawnThingOnRemoved>CNNetworkedHand</spawnThingOnRemoved>
		<comps>
			<li Class="CyberNet.HediffCompPropertiesCyberNetImplant">
				<compClass>CyberNet.HediffCompCyberNetImplant</compClass>
				<DefaultSeverity>1</DefaultSeverity>
				<BandwidthUsage>0.1</BandwidthUsage>
				<ProcessorUsage>0.05</ProcessorUsage>
			</li>
		</comps>
	</HediffDef>

	<ThingDef ParentName="CyberNetProsthetic">
		<defName>CNNetworkedHand</defName>
		<label>Networked hand</label>
		<description>A networked prosthetic that offloads processing to remote processors. Cheaper than self contained bionic hands, and more efficient, but requires infrastructure to function.</description>
		<statBases>
			<WorkToMake>16000</WorkToMake>
			<Mass>2</Mass>
		</statBases>
		<costList>
			<Plasteel>5</Plasteel>
			<ComponentIndustrial>3</ComponentIndustrial>
			<ComponentSpacer>1</ComponentSpacer>
		</costList>
		<recipeMaker>
			<skillRequirements>
				<Crafting>10</Crafting>
			</skillRequirements>
			<researchPrerequisite>CNNetworkedProsthetics</researchPrerequisite>
		</recipeMaker>
		<comps>
			<li Class="MSE2.CompProperties_IncludedChildParts">
				<standardChildren>
					<li>CNNetworkedFinger</li>
					<li>CNNetworkedFinger</li>
					<li>CNNetworkedFinger</li>
					<li>CNNetworkedFinger</li>
					<li>CNNetworkedFinger</li>
				</standardChildren>
			</li>
		</comps>
	</ThingDef>

	<RecipeDef ParentName="CyberNetSurgery">
		<defName>CNInstallNetworkedHand</defName>
		<label>Install networked hand</label>
		<description>Install a networked hand</description>
		<jobString>Installing networked hand</jobString>
		<workAmount>2500</workAmount>
		<ingredients>
			<li>
				<filter>
					<categories>
						<li>Medicine</li>
					</categories>
				</filter>
				<count>2</count>
			</li>
			<li>
				<filter>
					<thingDefs>
						<li>CNNetworkedHand</li>
					</thingDefs>
				</filter>
				<count>1</count>
			</li>
		</ingredients>
		<fixedIngredientFilter>
			<categories>
				<li>Medicine</li>
			</categories>
			<thingDefs>
				<li>CNNetworkedHand</li>
			</thingDefs>
		</fixedIngredientFilter>
		<appliedOnFixedBodyParts>
			<li>Hand</li>
		</appliedOnFixedBodyParts>
		<addsHediff>CNNetworkedHand</addsHediff>
	</RecipeDef>


	<!-- cnn finger -->

	<HediffDef ParentName="CNHediffProsthetic">
		<defName>CNNetworkedFinger</defName>
		<label>networked finger</label>
		<labelNoun>a networked finger</labelNoun>
		<description>A networked prosthetic that offloads processing to remote processors. Cheaper than self contained bionic fingers, and more efficient, but requires infrastructure to function.</description>
		<spawnThingOnRemoved>CNNetworkedFinger</spawnThingOnRemoved>
		<comps>
			<li Class="CyberNet.HediffCompPropertiesCyberNetImplant">
				<compClass>CyberNet.HediffCompCyberNetImplant</compClass>
				<DefaultSeverity>1</DefaultSeverity>
				<BandwidthUsage>0.04</BandwidthUsage>
				<ProcessorUsage>0.02</ProcessorUsage>
			</li>
		</comps>
	</HediffDef>

	<ThingDef ParentName="CyberNetProsthetic">
		<defName>CNNetworkedFinger</defName>
		<label>Networked finger</label>
		<description>A networked prosthetic that offloads processing to remote processors. Cheaper than self contained bionic fingers, and more efficient, but requires infrastructure to function.</description>
		<statBases>
			<WorkToMake>3000</WorkToMake>
			<Mass>0.2</Mass>
		</statBases>
		<costList>
			<Plasteel>2</Plasteel>
			<ComponentIndustrial>1</ComponentIndustrial>
		</costList>
		<recipeMaker>
			<skillRequirements>
				<Crafting>10</Crafting>
			</skillRequirements>
			<researchPrerequisite>CNNetworkedProsthetics</researchPrerequisite>
		</recipeMaker>
	</ThingDef>

	<RecipeDef ParentName="CyberNetSurgery">
		<defName>CNInstallNetworkedFinger</defName>
		<label>Install networked finger</label>
		<description>Install a networked finger</description>
		<jobString>Installing networked finger</jobString>
		<workAmount>2500</workAmount>
		<ingredients>
			<li>
				<filter>
					<categories>
						<li>Medicine</li>
					</categories>
				</filter>
				<count>2</count>
			</li>
			<li>
				<filter>
					<thingDefs>
						<li>CNNetworkedFinger</li>
					</thingDefs>
				</filter>
				<count>1</count>
			</li>
		</ingredients>
		<fixedIngredientFilter>
			<categories>
				<li>Medicine</li>
			</categories>
			<thingDefs>
				<li>CNNetworkedFinger</li>
			</thingDefs>
		</fixedIngredientFilter>
		<appliedOnFixedBodyParts>
			<li>Finger</li>
		</appliedOnFixedBodyParts>
		<addsHediff>CNNetworkedFinger</addsHediff>
	</RecipeDef>


	<!-- cnn foot -->

	<HediffDef ParentName="CNHediffProsthetic">
		<defName>CNNetworkedFoot</defName>
		<label>networked foot</label>
		<labelNoun>a networked foot</labelNoun>
		<description>A networked prosthetic that offloads processing to remote processors. Cheaper than self contained bionic feet, and more efficient, but requires infrastructure to function.</description>
		<spawnThingOnRemoved>CNNetworkedFoot</spawnThingOnRemoved>
		<comps>
			<li Class="CyberNet.HediffCompPropertiesCyberNetImplant">
				<compClass>CyberNet.HediffCompCyberNetImplant</compClass>
				<DefaultSeverity>1</DefaultSeverity>
				<BandwidthUsage>0.1</BandwidthUsage>
				<ProcessorUsage>0.05</ProcessorUsage>
			</li>
		</comps>
	</HediffDef>

	<ThingDef ParentName="CyberNetProsthetic">
		<defName>CNNetworkedFoot</defName>
		<label>Networked foot</label>
		<description>A networked prosthetic that offloads processing to remote processors. Cheaper than self contained bionic feet, and more efficient, but requires infrastructure to function.</description>
		<statBases>
			<WorkToMake>15000</WorkToMake>
			<Mass>2</Mass>
		</statBases>
		<costList>
			<Plasteel>8</Plasteel>
			<ComponentIndustrial>4</ComponentIndustrial>
			<ComponentSpacer>1</ComponentSpacer>
		</costList>
		<recipeMaker>
			<skillRequirements>
				<Crafting>10</Crafting>
			</skillRequirements>
			<researchPrerequisite>CNNetworkedProsthetics</researchPrerequisite>
		</recipeMaker>
		<comps>
			<li Class="MSE2.CompProperties_IncludedChildParts">
				<standardChildren>
					<li>CNNetworkedToe</li>
					<li>CNNetworkedToe</li>
					<li>CNNetworkedToe</li>
					<li>CNNetworkedToe</li>
					<li>CNNetworkedToe</li>
				</standardChildren>
			</li>
		</comps>
	</ThingDef>

	<RecipeDef ParentName="CyberNetSurgery">
		<defName>CNInstallNetworkedFoot</defName>
		<label>Install networked foot</label>
		<description>Install a networked foot</description>
		<jobString>Installing networked foot</jobString>
		<workAmount>2500</workAmount>
		<ingredients>
			<li>
				<filter>
					<categories>
						<li>Medicine</li>
					</categories>
				</filter>
				<count>2</count>
			</li>
			<li>
				<filter>
					<thingDefs>
						<li>CNNetworkedFoot</li>
					</thingDefs>
				</filter>
				<count>1</count>
			</li>
		</ingredients>
		<fixedIngredientFilter>
			<categories>
				<li>Medicine</li>
			</categories>
			<thingDefs>
				<li>CNNetworkedFoot</li>
			</thingDefs>
		</fixedIngredientFilter>
		<appliedOnFixedBodyParts>
			<li>Foot</li>
		</appliedOnFixedBodyParts>
		<addsHediff>CNNetworkedFoot</addsHediff>
	</RecipeDef>


	<!-- cnn toe -->

	<HediffDef ParentName="CNHediffProsthetic">
		<defName>CNNetworkedToe</defName>
		<label>networked toe</label>
		<labelNoun>a networked toe</labelNoun>
		<description>A networked prosthetic that offloads processing to remote processors. Cheaper than self contained bionic toes, and more efficient, but requires infrastructure to function.</description>
		<spawnThingOnRemoved>CNNetworkedToe</spawnThingOnRemoved>
		<comps>
			<li Class="CyberNet.HediffCompPropertiesCyberNetImplant">
				<compClass>CyberNet.HediffCompCyberNetImplant</compClass>
				<DefaultSeverity>1</DefaultSeverity>
				<BandwidthUsage>0.03</BandwidthUsage>
				<ProcessorUsage>0.015</ProcessorUsage>
			</li>
		</comps>
	</HediffDef>

	<ThingDef ParentName="CyberNetProsthetic">
		<defName>CNNetworkedToe</defName>
		<label>Networked toe</label>
		<description>A networked prosthetic that offloads processing to remote processors. Cheaper than self contained bionic toes, and more efficient, but requires infrastructure to function.</description>
		<statBases>
			<WorkToMake>2000</WorkToMake>
			<Mass>0.15</Mass>
		</statBases>
		<costList>
			<Plasteel>2</Plasteel>
			<ComponentIndustrial>1</ComponentIndustrial>
		</costList>
		<recipeMaker>
			<skillRequirements>
				<Crafting>10</Crafting>
			</skillRequirements>
			<researchPrerequisite>CNNetworkedProsthetics</researchPrerequisite>
		</recipeMaker>
	</ThingDef>

	<RecipeDef ParentName="CyberNetSurgery">
		<defName>CNInstallNetworkedToe</defName>
		<label>Install networked toe</label>
		<description>Install a networked toe</description>
		<jobString>Installing networked toe</jobString>
		<workAmount>2500</workAmount>
		<ingredients>
			<li>
				<filter>
					<categories>
						<li>Medicine</li>
					</categories>
				</filter>
				<count>2</count>
			</li>
			<li>
				<filter>
					<thingDefs>
						<li>CNNetworkedToe</li>
					</thingDefs>
				</filter>
				<count>1</count>
			</li>
		</ingredients>
		<fixedIngredientFilter>
			<categories>
				<li>Medicine</li>
			</categories>
			<thingDefs>
				<li>CNNetworkedToe</li>
			</thingDefs>
		</fixedIngredientFilter>
		<appliedOnFixedBodyParts>
			<li>Toe</li>
		</appliedOnFixedBodyParts>
		<addsHediff>CNNetworkedToe</addsHediff>
	</RecipeDef>



</Defs>